rcbsim/__init__.py
rcbsim/building_physics.py
rcbsim/emission_system.py
rcbsim/radiation.py
rcbsim/supply_system.py
rcbsim/auxiliary/__init__.py
rcbsim/auxiliary/epwreader.py
rcbsim/auxiliary/sun_position_reader.py
rcbsim-0.3b0.dist-info/LICENSE
rcbsim-0.3b0.dist-info/METADATA
rcbsim-0.3b0.dist-info/WHEEL
rcbsim-0.3b0.dist-info/top_level.txt
rcbsim-0.3b0.dist-info/RECORD
