Metadata-Version: 2.1
Name: rcbsim
Version: 0.3b0
Summary: A version of RC building simulator that is installable via pip forked from https://github.com/architecture-building-systems/RC_BuildingSimulator Oct  3, 2024 by dlvilla@sandia.gov
Author-email: Daniel Villa <dlvilla@sandia.gov>
License: MIT
Project-URL: Repository, https://github.com/dlvilla/rcbsim.git
Keywords: building energy models,RC models
Classifier: Programming Language :: Python :: 3
Classifier: License :: OSI Approved :: MIT License
Classifier: Operating System :: OS Independent
Requires-Python: >=3.9
License-File: LICENSE
Requires-Dist: numpy
Requires-Dist: setuptools
Requires-Dist: matplotlib
Requires-Dist: pandas
